{"courses":[{"score":19.67,"unit":2,"name":"elementum"},{"score":4.4,"unit":2,"name":"vel"},{"score":15.11,"unit":4,"name":"non"},{"score":6.5,"unit":3,"name":"eget"},{"score":15.84,"unit":2,"name":"purus"},{"score":9.51,"unit":2,"name":"ornare"},{"score":6.91,"unit":1,"name":"duis"},{"score":14.63,"unit":2,"name":"accumsan"},{"score":2.76,"unit":3,"name":"duis"},{"score":11.46,"unit":2,"name":"pede"},{"score":14.46,"unit":3,"name":"elementum"},{"score":7.94,"unit":1,"name":"gravida"},{"score":4.96,"unit":4,"name":"sit"},{"score":2.87,"unit":4,"name":"augue"},{"score":3.72,"unit":4,"name":"orci"},{"score":3.7,"unit":3,"name":"interdum"},{"score":19.77,"unit":2,"name":"imperdiet"},{"score":12.62,"unit":1,"name":"morbi"},{"score":1.02,"unit":1,"name":"et"},{"score":4.26,"unit":4,"name":"consectetuer"},{"score":11.52,"unit":3,"name":"tempus"},{"score":8.94,"unit":4,"name":"vel"},{"score":11.44,"unit":4,"name":"quisque"},{"score":5.31,"unit":4,"name":"semper"},{"score":8.45,"unit":4,"name":"turpis"},{"score":8.49,"unit":4,"name":"feugiat"},{"score":8.8,"unit":1,"name":"dignissim"},{"score":5.31,"unit":2,"name":"auctor"},{"score":1.82,"unit":2,"name":"augue"},{"score":3.63,"unit":2,"name":"neque"}],"average":8.254875,"id":"cb788926-242e-46b3-a48b-50dafa7e6dfa","full-name":"Danell Cowpe"}